odoo10_addon_purchase_cancel_qty-10.0.1.0.0.99.dev2-nspkg.pth
odoo/addons/purchase_cancel_qty/README.rst
odoo/addons/purchase_cancel_qty/__init__.py
odoo/addons/purchase_cancel_qty/__manifest__.py
odoo/addons/purchase_cancel_qty/init_hook.py
odoo/addons/purchase_cancel_qty/i18n/fr.po
odoo/addons/purchase_cancel_qty/i18n/purchase_cancel_qty.pot
odoo/addons/purchase_cancel_qty/models/__init__.py
odoo/addons/purchase_cancel_qty/models/purchase_order.py
odoo/addons/purchase_cancel_qty/models/purchase_order_line.py
odoo/addons/purchase_cancel_qty/static/description/icon.png
odoo/addons/purchase_cancel_qty/tests/__init__.py
odoo/addons/purchase_cancel_qty/tests/test_purchase_cancel_qty.py
odoo/addons/purchase_cancel_qty/views/purchase_order.xml
odoo/addons/purchase_cancel_qty/views/purchase_order_line.xml
odoo10_addon_purchase_cancel_qty-10.0.1.0.0.99.dev2.dist-info/METADATA
odoo10_addon_purchase_cancel_qty-10.0.1.0.0.99.dev2.dist-info/WHEEL
odoo10_addon_purchase_cancel_qty-10.0.1.0.0.99.dev2.dist-info/namespace_packages.txt
odoo10_addon_purchase_cancel_qty-10.0.1.0.0.99.dev2.dist-info/top_level.txt
odoo10_addon_purchase_cancel_qty-10.0.1.0.0.99.dev2.dist-info/RECORD
